opengeode_mymodule/__init__.py
opengeode_mymodule/mylib.py
opengeode_mymodule/lib64/libOpenGeode-MyModule_mylib.so
opengeode_mymodule/lib64/opengeode_mymodule_py_mylib.cpython-37m-x86_64-linux-gnu.so
OpenGeode_ModuleTemplate-2.0.0.dist-info/METADATA
OpenGeode_ModuleTemplate-2.0.0.dist-info/WHEEL
OpenGeode_ModuleTemplate-2.0.0.dist-info/top_level.txt
OpenGeode_ModuleTemplate-2.0.0.dist-info/RECORD
