Metadata-Version: 2.1
Name: OpenGeode-ModuleTemplate
Version: 2.0.0
Summary: Open source framework for representing and manipulating geometric models
Home-page: https://github.com/Geode-solutions/OpenGeode-MyModule
Author: Geode-solutions
Author-email: contact@geode-solutions.com
License: MIT
Platform: UNKNOWN
Requires-Dist: opengeode-core (==14.*,>=14.0.0)
